gigaam/__init__.py
gigaam/decoder.py
gigaam/decoding.py
gigaam/encoder.py
gigaam/model.py
gigaam/onnx_utils.py
gigaam/preprocess.py
gigaam/utils.py
gigaam/vad_utils.py
gigaam-0.1.0.dist-info/LICENSE
gigaam-0.1.0.dist-info/METADATA
gigaam-0.1.0.dist-info/WHEEL
gigaam-0.1.0.dist-info/top_level.txt
gigaam-0.1.0.dist-info/RECORD
