Metadata-Version: 2.1
Name: gigaam
Version: 0.1.0
Summary: GigaAM: A package for audio modeling and ASR.
Home-page: https://github.com/salute-developers/GigaAM/
Author: GigaChat Team
License: MIT
Requires-Python: >=3.8
License-File: LICENSE
Requires-Dist: hydra-core <=1.3.2
Requires-Dist: numpy
Requires-Dist: omegaconf <=2.3.0
Requires-Dist: pydub <=0.25.1
Requires-Dist: sentencepiece <=0.2.0
Requires-Dist: torch <=2.5.1
Requires-Dist: torchaudio <=2.5.1
Requires-Dist: onnx ==1.17.0
Requires-Dist: onnxruntime ==1.17.3
Requires-Dist: tqdm
Provides-Extra: longform
Requires-Dist: pyannote.audio ; extra == 'longform'
Requires-Dist: pydub ; extra == 'longform'
